{
  "width": 320,
  "height": 240,
  "offsetX": 0,
  "offsetY": 0,
  "layers": [
    {
      "name": "tiles",
      "_eid": "37713875",
      "offsetX": 0,
      "offsetY": 0,
      "gridCellWidth": 16,
      "gridCellHeight": 16,
      "gridCellsX": 20,
      "gridCellsY": 15,
      "tileset": "tileset",
      "data2D": [
        [
          0,
          50,
          34,
          35,
          0,
          29,
          0,
          0,
          0,
          0,
          0,
          0,
          0,
          52,
          53,
          0,
          0,
          0,
          1,
          0
        ],
        [
          35,
          58,
          42,
          43,
          34,
          35,
          0,
          4,
          2,
          2,
          2,
          2,
          2,
          60,
          61,
          0,
          0,
          0,
          12,
          2
        ],
        [
          43,
          34,
          35,
          50,
          42,
          43,
          0,
          1,
          0,
          10,
          11,
          11,
          53,
          61,
          0,
          16,
          17,
          17,
          17,
          18
        ],
        [
          0,
          42,
          43,
          50,
          0,
          1,
          0,
          1,
          0,
          51,
          34,
          35,
          50,
          50,
          58,
          59,
          24,
          25,
          27,
          51
        ],
        [
          0,
          0,
          15,
          0,
          54,
          47,
          39,
          39,
          47,
          57,
          42,
          43,
          57,
          32,
          33,
          57,
          0,
          0,
          0,
          56
        ],
        [
          2,
          2,
          15,
          2,
          38,
          13,
          0,
          1,
          0,
          0,
          48,
          56,
          57,
          40,
          41,
          61,
          0,
          0,
          0,
          0
        ],
        [
          0,
          0,
          14,
          0,
          46,
          0,
          0,
          1,
          0,
          0,
          62,
          47,
          55,
          1,
          36,
          37,
          52,
          0,
          31,
          0
        ],
        [
          34,
          35,
          48,
          56,
          48,
          49,
          0,
          12,
          2,
          2,
          2,
          2,
          38,
          13,
          44,
          45,
          53,
          0,
          46,
          0
        ],
        [
          42,
          43,
          56,
          32,
          33,
          48,
          0,
          0,
          0,
          50,
          0,
          0,
          46,
          0,
          0,
          61,
          60,
          54,
          63,
          0
        ],
        [
          56,
          48,
          48,
          40,
          41,
          4,
          21,
          0,
          50,
          34,
          35,
          0,
          38,
          29,
          9,
          52,
          52,
          53,
          9,
          11
        ],
        [
          61,
          53,
          0,
          38,
          62,
          39,
          47,
          34,
          35,
          42,
          43,
          50,
          62,
          47,
          56,
          50,
          58,
          50,
          34,
          35
        ],
        [
          52,
          39,
          47,
          63,
          2,
          13,
          0,
          42,
          43,
          15,
          58,
          62,
          55,
          1,
          48,
          32,
          33,
          56,
          42,
          43
        ],
        [
          8,
          16,
          17,
          17,
          17,
          17,
          18,
          11,
          11,
          14,
          8,
          10,
          46,
          1,
          0,
          40,
          41,
          57,
          57,
          56
        ],
        [
          50,
          58,
          24,
          25,
          26,
          27,
          34,
          35,
          50,
          51,
          50,
          59,
          38,
          13,
          30,
          0,
          0,
          52,
          57,
          32
        ],
        [
          32,
          33,
          0,
          0,
          6,
          0,
          42,
          43,
          49,
          49,
          57,
          49,
          56,
          0,
          38,
          0,
          0,
          60,
          53,
          40
        ]
      ],
      "exportMode": 0,
      "arrayMode": 1
    }
  ]
}